{"name":"Diana","champSkins":[{"skinName":"Diana","skinInfo":{"skinAvatar":"C:\\Users\\fg\\Desktop\\work\\el-botola\\scraping-league-node\\downloads\\skins\\Diana\\diana\\avatar.png","skinSplash":"C:\\Users\\fg\\Desktop\\work\\el-botola\\scraping-league-node\\downloads\\skins\\Diana\\diana\\splash.jpg"}},{"skinName":"Dark Valkyrie Diana","skinInfo":{"skinAvatar":"C:\\Users\\fg\\Desktop\\work\\el-botola\\scraping-league-node\\downloads\\skins\\Diana\\dark-valkyrie-diana\\avatar.png","skinSplash":"C:\\Users\\fg\\Desktop\\work\\el-botola\\scraping-league-node\\downloads\\skins\\Diana\\dark-valkyrie-diana\\splash.jpg"}},{"skinName":"Lunar Goddess Diana","skinInfo":{"skinAvatar":"C:\\Users\\fg\\Desktop\\work\\el-botola\\scraping-league-node\\downloads\\skins\\Diana\\lunar-goddess-diana\\avatar.png","skinSplash":"C:\\Users\\fg\\Desktop\\work\\el-botola\\scraping-league-node\\downloads\\skins\\Diana\\lunar-goddess-diana\\splash.jpg"}},{"skinName":"Infernal Diana","skinInfo":{"skinAvatar":"C:\\Users\\fg\\Desktop\\work\\el-botola\\scraping-league-node\\downloads\\skins\\Diana\\infernal-diana\\avatar.png","skinSplash":"C:\\Users\\fg\\Desktop\\work\\el-botola\\scraping-league-node\\downloads\\skins\\Diana\\infernal-diana\\splash.jpg"}},{"skinName":"Blood Moon Diana","skinInfo":{"skinAvatar":"C:\\Users\\fg\\Desktop\\work\\el-botola\\scraping-league-node\\downloads\\skins\\Diana\\blood-moon-diana\\avatar.png","skinSplash":"C:\\Users\\fg\\Desktop\\work\\el-botola\\scraping-league-node\\downloads\\skins\\Diana\\blood-moon-diana\\splash.jpg"}},{"skinName":"Dark Waters Diana","skinInfo":{"skinAvatar":"C:\\Users\\fg\\Desktop\\work\\el-botola\\scraping-league-node\\downloads\\skins\\Diana\\dark-waters-diana\\avatar.png","skinSplash":"C:\\Users\\fg\\Desktop\\work\\el-botola\\scraping-league-node\\downloads\\skins\\Diana\\dark-waters-diana\\splash.jpg"}},{"skinName":"Dragonslayer Diana","skinInfo":{"skinAvatar":"C:\\Users\\fg\\Desktop\\work\\el-botola\\scraping-league-node\\downloads\\skins\\Diana\\dragonslayer-diana\\avatar.png","skinSplash":"C:\\Users\\fg\\Desktop\\work\\el-botola\\scraping-league-node\\downloads\\skins\\Diana\\dragonslayer-diana\\splash.jpg"}}]}