{"name":"Galio","champSkins":[{"skinName":"Galio","skinInfo":{"skinAvatar":"C:\\Users\\fg\\Desktop\\work\\el-botola\\scraping-league-node\\downloads\\skins\\Galio\\galio\\avatar.png","skinSplash":"C:\\Users\\fg\\Desktop\\work\\el-botola\\scraping-league-node\\downloads\\skins\\Galio\\galio\\splash.jpg"}},{"skinName":"Enchanted Galio","skinInfo":{"skinAvatar":"C:\\Users\\fg\\Desktop\\work\\el-botola\\scraping-league-node\\downloads\\skins\\Galio\\enchanted-galio\\avatar.png","skinSplash":"C:\\Users\\fg\\Desktop\\work\\el-botola\\scraping-league-node\\downloads\\skins\\Galio\\enchanted-galio\\splash.jpg"}},{"skinName":"Hextech Galio","skinInfo":{"skinAvatar":"C:\\Users\\fg\\Desktop\\work\\el-botola\\scraping-league-node\\downloads\\skins\\Galio\\hextech-galio\\avatar.png","skinSplash":"C:\\Users\\fg\\Desktop\\work\\el-botola\\scraping-league-node\\downloads\\skins\\Galio\\hextech-galio\\splash.jpg"}},{"skinName":"Commando Galio","skinInfo":{"skinAvatar":"C:\\Users\\fg\\Desktop\\work\\el-botola\\scraping-league-node\\downloads\\skins\\Galio\\commando-galio\\avatar.png","skinSplash":"C:\\Users\\fg\\Desktop\\work\\el-botola\\scraping-league-node\\downloads\\skins\\Galio\\commando-galio\\splash.jpg"}},{"skinName":"Gatekeeper Galio","skinInfo":{"skinAvatar":"C:\\Users\\fg\\Desktop\\work\\el-botola\\scraping-league-node\\downloads\\skins\\Galio\\gatekeeper-galio\\avatar.png","skinSplash":"C:\\Users\\fg\\Desktop\\work\\el-botola\\scraping-league-node\\downloads\\skins\\Galio\\gatekeeper-galio\\splash.jpg"}},{"skinName":"Debonair Galio","skinInfo":{"skinAvatar":"C:\\Users\\fg\\Desktop\\work\\el-botola\\scraping-league-node\\downloads\\skins\\Galio\\debonair-galio\\avatar.png","skinSplash":"C:\\Users\\fg\\Desktop\\work\\el-botola\\scraping-league-node\\downloads\\skins\\Galio\\debonair-galio\\splash.jpg"}},{"skinName":"Birdio","skinInfo":{"skinAvatar":"C:\\Users\\fg\\Desktop\\work\\el-botola\\scraping-league-node\\downloads\\skins\\Galio\\birdio\\avatar.png","skinSplash":"C:\\Users\\fg\\Desktop\\work\\el-botola\\scraping-league-node\\downloads\\skins\\Galio\\birdio\\splash.jpg"}},{"skinName":"Infernal Galio","skinInfo":{"skinAvatar":"C:\\Users\\fg\\Desktop\\work\\el-botola\\scraping-league-node\\downloads\\skins\\Galio\\infernal-galio\\avatar.png","skinSplash":"C:\\Users\\fg\\Desktop\\work\\el-botola\\scraping-league-node\\downloads\\skins\\Galio\\infernal-galio\\splash.jpg"}}]}