{"name":"Kayle","champSkins":[{"skinName":"Kayle","skinInfo":{"skinAvatar":"C:\\Users\\fg\\Desktop\\work\\el-botola\\scraping-league-node\\downloads\\skins\\Kayle\\kayle\\avatar.png","skinSplash":"C:\\Users\\fg\\Desktop\\work\\el-botola\\scraping-league-node\\downloads\\skins\\Kayle\\kayle\\splash.jpg"}},{"skinName":"Silver Kayle","skinInfo":{"skinAvatar":"C:\\Users\\fg\\Desktop\\work\\el-botola\\scraping-league-node\\downloads\\skins\\Kayle\\silver-kayle\\avatar.png","skinSplash":"C:\\Users\\fg\\Desktop\\work\\el-botola\\scraping-league-node\\downloads\\skins\\Kayle\\silver-kayle\\splash.jpg"}},{"skinName":"Viridian Kayle","skinInfo":{"skinAvatar":"C:\\Users\\fg\\Desktop\\work\\el-botola\\scraping-league-node\\downloads\\skins\\Kayle\\viridian-kayle\\avatar.png","skinSplash":"C:\\Users\\fg\\Desktop\\work\\el-botola\\scraping-league-node\\downloads\\skins\\Kayle\\viridian-kayle\\splash.jpg"}},{"skinName":"Transcended Kayle","skinInfo":{"skinAvatar":"C:\\Users\\fg\\Desktop\\work\\el-botola\\scraping-league-node\\downloads\\skins\\Kayle\\transcended-kayle\\avatar.png","skinSplash":"C:\\Users\\fg\\Desktop\\work\\el-botola\\scraping-league-node\\downloads\\skins\\Kayle\\transcended-kayle\\splash.jpg"}},{"skinName":"Battleborn Kayle","skinInfo":{"skinAvatar":"C:\\Users\\fg\\Desktop\\work\\el-botola\\scraping-league-node\\downloads\\skins\\Kayle\\battleborn-kayle\\avatar.png","skinSplash":"C:\\Users\\fg\\Desktop\\work\\el-botola\\scraping-league-node\\downloads\\skins\\Kayle\\battleborn-kayle\\splash.jpg"}},{"skinName":"Judgment Kayle","skinInfo":{"skinAvatar":"C:\\Users\\fg\\Desktop\\work\\el-botola\\scraping-league-node\\downloads\\skins\\Kayle\\judgment-kayle\\avatar.png","skinSplash":"C:\\Users\\fg\\Desktop\\work\\el-botola\\scraping-league-node\\downloads\\skins\\Kayle\\judgment-kayle\\splash.jpg"}},{"skinName":"Aether Wing Kayle","skinInfo":{"skinAvatar":"C:\\Users\\fg\\Desktop\\work\\el-botola\\scraping-league-node\\downloads\\skins\\Kayle\\aether-wing-kayle\\avatar.png","skinSplash":"C:\\Users\\fg\\Desktop\\work\\el-botola\\scraping-league-node\\downloads\\skins\\Kayle\\aether-wing-kayle\\splash.jpg"}},{"skinName":"Riot Kayle","skinInfo":{"skinAvatar":"C:\\Users\\fg\\Desktop\\work\\el-botola\\scraping-league-node\\downloads\\skins\\Kayle\\riot-kayle\\avatar.png","skinSplash":"C:\\Users\\fg\\Desktop\\work\\el-botola\\scraping-league-node\\downloads\\skins\\Kayle\\riot-kayle\\splash.jpg"}},{"skinName":"Iron Inquisitor Kayle","skinInfo":{"skinAvatar":"C:\\Users\\fg\\Desktop\\work\\el-botola\\scraping-league-node\\downloads\\skins\\Kayle\\iron-inquisitor-kayle\\avatar.png","skinSplash":"C:\\Users\\fg\\Desktop\\work\\el-botola\\scraping-league-node\\downloads\\skins\\Kayle\\iron-inquisitor-kayle\\splash.jpg"}},{"skinName":"Pentakill Kayle","skinInfo":{"skinAvatar":"C:\\Users\\fg\\Desktop\\work\\el-botola\\scraping-league-node\\downloads\\skins\\Kayle\\pentakill-kayle\\avatar.png","skinSplash":"C:\\Users\\fg\\Desktop\\work\\el-botola\\scraping-league-node\\downloads\\skins\\Kayle\\pentakill-kayle\\splash.jpg"}}]}