{"name":"Nasus","champSkins":[{"skinName":"Nasus","skinInfo":{"skinAvatar":"C:\\Users\\fg\\Desktop\\work\\el-botola\\scraping-league-node\\downloads\\skins\\Nasus\\nasus\\avatar.png","skinSplash":"C:\\Users\\fg\\Desktop\\work\\el-botola\\scraping-league-node\\downloads\\skins\\Nasus\\nasus\\splash.jpg"}},{"skinName":"Galactic Nasus","skinInfo":{"skinAvatar":"C:\\Users\\fg\\Desktop\\work\\el-botola\\scraping-league-node\\downloads\\skins\\Nasus\\galactic-nasus\\avatar.png","skinSplash":"C:\\Users\\fg\\Desktop\\work\\el-botola\\scraping-league-node\\downloads\\skins\\Nasus\\galactic-nasus\\splash.jpg"}},{"skinName":"Pharaoh Nasus","skinInfo":{"skinAvatar":"C:\\Users\\fg\\Desktop\\work\\el-botola\\scraping-league-node\\downloads\\skins\\Nasus\\pharaoh-nasus\\avatar.png","skinSplash":"C:\\Users\\fg\\Desktop\\work\\el-botola\\scraping-league-node\\downloads\\skins\\Nasus\\pharaoh-nasus\\splash.jpg"}},{"skinName":"Dreadknight Nasus","skinInfo":{"skinAvatar":"C:\\Users\\fg\\Desktop\\work\\el-botola\\scraping-league-node\\downloads\\skins\\Nasus\\dreadknight-nasus\\avatar.png","skinSplash":"C:\\Users\\fg\\Desktop\\work\\el-botola\\scraping-league-node\\downloads\\skins\\Nasus\\dreadknight-nasus\\splash.jpg"}},{"skinName":"Riot K-9 Nasus","skinInfo":{"skinAvatar":"C:\\Users\\fg\\Desktop\\work\\el-botola\\scraping-league-node\\downloads\\skins\\Nasus\\riot-k-9-nasus\\avatar.png","skinSplash":"C:\\Users\\fg\\Desktop\\work\\el-botola\\scraping-league-node\\downloads\\skins\\Nasus\\riot-k-9-nasus\\splash.jpg"}},{"skinName":"Infernal Nasus","skinInfo":{"skinAvatar":"C:\\Users\\fg\\Desktop\\work\\el-botola\\scraping-league-node\\downloads\\skins\\Nasus\\infernal-nasus\\avatar.png","skinSplash":"C:\\Users\\fg\\Desktop\\work\\el-botola\\scraping-league-node\\downloads\\skins\\Nasus\\infernal-nasus\\splash.jpg"}},{"skinName":"Archduke Nasus","skinInfo":{"skinAvatar":"C:\\Users\\fg\\Desktop\\work\\el-botola\\scraping-league-node\\downloads\\skins\\Nasus\\archduke-nasus\\avatar.png","skinSplash":"C:\\Users\\fg\\Desktop\\work\\el-botola\\scraping-league-node\\downloads\\skins\\Nasus\\archduke-nasus\\splash.jpg"}},{"skinName":"Worldbreaker Nasus","skinInfo":{"skinAvatar":"C:\\Users\\fg\\Desktop\\work\\el-botola\\scraping-league-node\\downloads\\skins\\Nasus\\worldbreaker-nasus\\avatar.png","skinSplash":"C:\\Users\\fg\\Desktop\\work\\el-botola\\scraping-league-node\\downloads\\skins\\Nasus\\worldbreaker-nasus\\splash.jpg"}},{"skinName":"Lunar Guardian Nasus","skinInfo":{"skinAvatar":"C:\\Users\\fg\\Desktop\\work\\el-botola\\scraping-league-node\\downloads\\skins\\Nasus\\lunar-guardian-nasus\\avatar.png","skinSplash":"C:\\Users\\fg\\Desktop\\work\\el-botola\\scraping-league-node\\downloads\\skins\\Nasus\\lunar-guardian-nasus\\splash.jpg"}}]}